<?xml version="1.0" encoding="UTF-8"?>
<root>
  <object Faceable = "false" SCover ="0" Surface = "true">
    <sprite name="Environment/Surfaces/ground" offset= "0,0">
      <variation id="0" weight="10"/>
      <variation id="1" weight="10"/>
      <variation id="2" weight="5"/>
      <variation id="5" weight="10"/>
	  <variation id="6" weight="30"/>
      <variation id="7" weight="30"/>
      <variation id="3" weight="1"/>
      <variation id="4" weight="1"/>
      <variation id="8" weight="1"/>
    </sprite>
    <name>basicFloor</name>
  </object>
  <object Faceable = "true" SCover ="0" Surface = "true">
    <sprite name="Environment/Surfaces/roadStripe0" offset= "0,0"/>
    <name>Striped Road</name>
  </object>
  <object Faceable = "false" SCover ="0" Impassible = "true" Surface = "true">
    <sprite name="Environment/Surfaces/water" variations = "1" offset= "0,0"/>
    <name>water</name>
  </object>
  <object Faceable = "false" SCover ="0" Surface = "true">
    <sprite name="Environment/Surfaces/capturePoint" offset= "0,0"/>
    <name>capturePoint</name>
  </object>
  <object Faceable = "false" SCover ="0" Surface = "true">
    <sprite name="Environment/Surfaces/spawnPoint1" offset= "0,0"/>
    <name>spawnPointT1</name>
  </object>
  <object Faceable = "false" SCover ="0" Surface = "true">
    <sprite name="Environment/Surfaces/spawnPoint2"  offset= "0,0"/>
    <name>spawnPointT2</name>
  </object>
  <object SCover = "3" Edge = "true" Health="15">
    <sprite  name="Environment/basicWall"  offset= "0,0"/>
    <name>basicWall</name>
    <destroyConsequences range = "1" >
      <place name="basicWallDebris"/>
    </destroyConsequences>
  </object>
  <object SCover = "3" Edge = "true" Health="1000">
    <sprite  name="Environment/borderWall"  offset= "0,0"/>
    <name>borderWall</name>
    <destroyConsequences range = "1" >
      <place name="basicWallDebris"/>
    </destroyConsequences>
  </object>
  <object SCover = "0" Edge = "true" Health="5">
    <sprite  name="Environment/destroyedWall"  offset= "0,0"/>
    <name>basicWallDebris</name>
  </object>
  <object VCover = "0" SCover = "3" Edge = "true" Health="3">
    <sprite  name="Environment/glassWall"  offset= "0,0"/>
    <name>glassWall</name>
  </object>
  <object VCover="3" SCover = "0" Edge = "true" Health="6">
    <sprite  name="Environment/strawWall"  offset= "0,0"/>
    <name>strawWall</name>
  </object>
  <object VCover = "0" SCover = "3" Edge = "true" Health="1">
    <sprite  name="Environment/paperMache"  offset= "0,0"/>
    <name>paperMache</name>
  </object>
  <object SCover = "2" Edge = "true">
    <sprite  name="Environment/basicHalfWall" offset= "0,0"  Health="10"/>
    <name>basicHalfWall</name>
    <destroyConsequences range = "1" >
      <place name="basicWallDebris"/>
    </destroyConsequences>
  </object>
  <object SCover = "1" Edge = "true">
    <sprite name="Environment/basicHalfWallLight" Health="6" offset= "0,0"/>
    <name>basicHalfWallLight</name>
    <destroyConsequences range = "1" >
      <place name="basicWallDebris"/>
    </destroyConsequences>
  </object>

  <unit Health="13" moveRange = "6" moves="2" determination="3" z="0.1">
    <name>Grunt</name>
    <action moveCost="1" actCost="1">
      <name>Attack</name>
      <targetAid>enemy</targetAid>

      <shoot dmg ="7" detRes="1" supression="1" supressionRange="2" dropOffRange="18"/>
      
      <effect>
        <consequences>
          <vfx name="clmagnitude" target="20" speed="50"/>
          <vfx name="noise" target="0.5" speed="100"/>
          <sfx name="rifle3"/>
        </consequences>
      </effect>
    </action>
    
    <action det ="2" moveCost="1" actCost="1">
      <name>Headshot</name>
      <tip>15 damage shot. Can only target targets with 0 determination. Great for punishing reckless ability usage</tip>
      <targetAid>enemy</targetAid>
      
      <shoot dmg ="15" detRes="15" supression="0" supressionRange="0" dropOffRange="20"/>
      
      <effect>
        <consequences>
          <vfx name="clmagnitude" target="20" speed="50"/>
          <vfx name="noise" target="0.5" speed="100"/>
          <sfx name="rifle"/>
        </consequences>
      </effect>
    </action>
  </unit>

  <unit Health="8" moveRange = "5" moves="3" determination="3" sightrange="18">
    <name>Scout</name>

    <action moveCost="1" actCost="1">
      <name>Attack</name>
      <targetAid>enemy</targetAid>
      
      <shoot dmg ="8" detRes="1" supression="1" supressionRange="1" dropOffRange="6"/>
      <effect>
        <consequences>
          <vfx name="clmagnitude" target="20" speed="50"/>
          <vfx name="noise" target="1" speed="100"/>
          <sfx name="shotgun"/>
        </consequences>
      </effect>
    </action>

    <action immideate="true" moveCost="0" actCost="0" detCost ="3">
      <name>Breach n Clear</name>
      <tip>Restores actions points and gives 5 movement points with short range. Great for covering lots of ground and maneuvering in close quarters</tip>
      <effect>
        <consequences>
          <applystatus status="BreachnClear" duration="1"/>
        </consequences>
      </effect>
    </action>

  </unit>
  
  <!--
    <unit Health="16" z="0.1"  moveRange = "3" moves="2" actions="2"  overwatch="3" determination="5">
      <name>Heavy</name>
      
      <spawneffect>
        <applystatus status="Holstered"/>
      </spawneffect>
  
      <action moveCost="1" actCost="1">
        <name>Attack</name>
        <targetAid>enemy</targetAid>
        <shoot dmg ="6" detRes="1" supression="1" supressionRange="3" dropOffRange="12"/>
        <effect>
          <vfx name="clmagnitude" target="20" speed="50"/>
          <vfx name="noise" target="0.5" speed="100"/>
          <sfx name="mg"/>
        </effect>
      </action>
  
      <action detCost ="3" moveCost="1" actCost="2">
        <name>Suppress</name>
        <tip>Shoot multiple shots int a dense area. Great for suppressing groups of enemies and punishing predictable plays</tip>
        
        <shoot dmg ="4" detRes="1" supression="1" supressionRange="3" dropOffRange="12"/>
        <shoot offset ="2,0" dmg ="2" detRes="1" supression="1" supressionRange="3" dropOffRange="12"/>
        <shoot offset ="-2,0" dmg ="2" detRes="1" supression="1" supressionRange="3" dropOffRange="12"/>
        <shoot offset ="0,2" dmg ="2" detRes="1" supression="1" supressionRange="3" dropOffRange="12"/>
        <shoot offset ="0,-2" dmg ="2" detRes="1" supression="1" supressionRange="3" dropOffRange="12"/>
        
        <effect>
          <consequences>
            <vfx name="clmagnitude" target="5" speed="50"/>
            <vfx name="noise" target="0.1" speed="100"/>
            <sfx name="mg"/>
          </consequences>
        </effect>
      </action>
  
      <toggleaction>
        <toggleoff  detCost ="1" moveCost="0" actCost="0">
          <name>Holster</name>
          <tip>Switch to mobility mode. Starts every turn with 4 move points</tip>
          <effect>
            <consequences>
              <applystatus status="Holstered"/>
            </consequences>
          </effect>
        </toggleoff>
        <toggleon name="" tip="" detCost ="1" moveCost="2" actCost="0">
          <name>UnHolster</name>
          <tip>Switch to attack mode. Starts every turn with 2 move points and 2 action points. Use once in a good position to be able to attack</tip>
          <effect>
            <consequences>
              <removestatus status="Holstered"/>
            </consequences>
          </effect>
        </toggleon>
      </toggleaction>
  
    </unit>
  
    <unit Health="8" z="0.1" moveRange = "4" moves="3" actions="1" determination="5"  sightrange="20">
      <name>Officer</name>
  
      <action moveCost="1" actCost="1">
        <name>Attack</name>
        <targetAid>enemy</targetAid>
        <shoot dmg ="6" detRes="1" supression="1" supressionRange="2" dropOffRange="12"/>
        <effect>
          <vfx name="clmagnitude" target="20" speed="50"/>
          <vfx name="noise" target="1" speed="100"/>
          <sfx name="rifle"/>
        </effect>
      </action>
  
      <action immideate="true" detCost ="2" moveCost="0" actCost="0">
        <name>Rally</name>
        <tip>All nearby friendlies stop panicking and gain full determiation</tip>
        
        <effect>
          <consequences visible ="false" los="true" range = "7" exRange="1" target="friend" ignore="Officer">
            <damage det="-100"/>
          </consequences>
        </effect>
      </action>
  
      <action detCost ="1" moveCost="1" actCost="0">
        <name>Command</name>
        <tip>Give a targeted unit 2 determination, 1 action point and 1 move point</tip>
        
  
        <effect range="1" visible ="false" target="friend">
          <delivery>
            <vissionCast range="22"/>
          </delivery>
          <consequences>
            <applystatus status="Boost" duration="1"/>
          </consequences>
        </effect>
      </action>
  
  
    </unit>
  
    <unit Health="10" z="0.1" moveRange = "4" inventory="5"  moves="3" actions="1" determination="2">
      <name>Specialist</name>
  
      <action moveCost="1" actCost="1">
        
        <targetAid>enemy</targetAid>
        
        <shoot dmg ="6" detRes="1" supression="1" supressionRange="2" dropOffRange="9"/>
        <effect>
          <consequences>
            <vfx name="clmagnitude" target="20" speed="50"/>
            <vfx name="noise" target="1" speed="100"/>
            <sfx name="rifle"/>
          </consequences>
        </effect>
      </action>
  
      <action detCost ="1" moveCost="1" actCost="1">
        <name>Resupply</name>
        <tip>Give a targeted unit their last used item back</tip>
        <targetAid>unit</targetAid>
        
        <effect>
          <delivery>
            <throwable throwRange="3"/>
          </delivery>
          <consequences>
            <giveItem item="{target.LastItem.Name}"/>
          </consequences>
        </effect>
      </action>
      
      <action detCost ="1" moveCost="1" actCost="1">
        <name>Resupply</name>
        <tip>Give a targeted unit item currently equipped by this unit</tip>
        <targetAid>unit</targetAid>
  
        <effect>
          <delivery>
            <throwable throwRange="3"/>
          </delivery>
          <consequences>
            <giveItem item="{target.SelectedItem.Name}"/>
          </consequences>
        </effect>
      </action>
      
    </unit>
  -->
  <statuseffect>
    <name>Holstered</name>
    <effect>
      <consequences>
      <values act ="[set]0" move="2"/>
    </consequences>
  </effect>
  </statuseffect>
  
  <statuseffect>
    <name>BreachnClear</name>
    
    <effect>
      <consequences>
       <values act ="1[set]" move="5[set]" moveRange="-3"/>
      </consequences>
    </effect>
  </statuseffect>
  
  <statuseffect>
    <name>Boost</name>
    
    <effect>
      <consequences>
        <values act ="1[cap]" move="1[cap]" moveRange="0"/>
      </consequences>
    </effect>
  </statuseffect>
  
  
  <object VCover = "0" Faceable = "false" SCover ="0" lifetime ="2">
    <sprite name="Environment/satchel"  offset= "0,0"/>
    <name>Satchel</name>
    
    <destroyConsequences range="2">
        <damage det="1" dmg="15"/>
        <vfx name="tintR" target="5" speed="50"/>
        <vfx name="clmagnitude" target="100" speed="50"/>
        <vfx name="noise" target="3" speed="60"/>
        <sfx name="grenade"/>
        <place name="Crater"/>
        <fowSpot scatter="4"/>
    </destroyConsequences>
  </object>


  <object VCover = "0" Faceable = "false" SCover ="0" z="0">
    <sprite name="Environment/crater"  offset= "0,0"/>
    <name>Crater</name>
  </object>


  <object VCover = "+5" Faceable = "false" SCover ="0" lifetime ="5" z="0.3">
    <sprite name="Environment/Smoke"  offset= "0,0"/>
    <name>Smoke</name>
  </object>

  <item>
    <name>Satchel Charge</name>
    <tip>Blows up after 1 turn dealing huge damage. Best for destroying enviroment</tip>

    <effect>
      <delivery>
        <throwable throwRange="4"/>
      </delivery>
      <consequences range="1">
        <place name="Satchel"/>
      </consequences>
    </effect>

  </item>

  <item>
    <name>Frag</name>
    <tip>Damages units in effect area</tip>
    <availability>Specialist</availability>
   
    <effect>
      <delivery>
        <throwable throwRange="6"/>
      </delivery>
      <consequences range="3">
        <damage det="1" dmg="5"/>
        <vfx name="tintR" target="5" speed="50"/>
        <vfx name="tintG" target="5" speed="50"/>
        <vfx name="clmagnitude" target="100" speed="50"/>
        <vfx name="noise" target="2" speed="50"/>
        <sfx name="grenade"/>
        <place name="Crater"/>
        <fowSpot scatter="4"/>
      </consequences>
    </effect>
  </item>

  <item>
    <name>Flash</name>
    <tip>Immideately panics units in effect radius</tip>

    
    <effect range="3">
      <delivery>
        <throwable throwRange="6"/>
      </delivery>
      <consequences range="3">
        <damage det="100" dmg="0"/>
        <vfx name="tintR" target="20" speed="50"/>
        <vfx name="tintG" target="20" speed="50"/>
        <vfx name="tintB" target="20" speed="50"/>
        <vfx name="clmagnitude" target="50" speed="50"/>
        <vfx name="noise" target="1" speed="50"/>
        <sfx name="bang"/>
        <fowSpot scatter="4"/>
      </consequences>
    </effect>
  </item>

  <item>
    <name>Smoke</name>
    <tip>Blocks line of sight</tip>

    <delivery>
      <throwable throwRange="7"/>
    </delivery>
    <consequences range="3">
      <place name="Smoke"/>
      <vfx name="clmagnitude" target="100" speed="40"/>
      <vfx name="noise" target="0.5" speed="50"/>
      <sfx name="smoke"/>
    </consequences>
  </item>

</root>